{
    "id": "sledite-ostavat",
    "title": "Следите остават",
    "images": [
        "img/films/sledite-ostavat.jpg",
        "img/films/sledite-ostavat-1.jpg",
        "img/films/sledite-ostavat-2.jpg",
        "img/films/sledite-ostavat-3.jpg",
        "img/films/sledite-ostavat-4.jpg"
    ],
    "director": "Петър Василев",
    "year": "1956 г.",
    "duration": "82 минути",
    "genre": "Приключенски, Драма",
    "cast": "Стефан Данаилов, Вера Драгостинова, Красимир Медарев, Георги Наумов",
    "summary": "На тротоара пред жилищните блокове на тиха софийска улица играят деца. От един прозорец пада секретен ключ. Децата го предават на живеещия там Тороманов, който идва да го търси. Оказва се, че малкият Пешо е дал по погрешка своя ключ. Иска да го смени и разбира, че ключът не е от апартамента на техния съсед. Тогава децата решават да открият истината. С хитрост и изобретателност малките разузнавачи откриват опасни диверсанти, които се крият в чужд апартамент."
}